fritzcollectd.py
fritzcollectd-0.1.0.dist-info/top_level.txt
fritzcollectd-0.1.0.dist-info/WHEEL
fritzcollectd-0.1.0.dist-info/DESCRIPTION.rst
fritzcollectd-0.1.0.dist-info/metadata.json
fritzcollectd-0.1.0.dist-info/RECORD
fritzcollectd-0.1.0.dist-info/METADATA
