Metadata-Version: 2.0
Name: fritzcollectd
Version: 0.1.0
Summary: A collectd plugin for monitoring AVM FRITZ!Box routers
Home-page: https://github.com/fetzerch/fritzcollectd
Author: Christian Fetzer
Author-email: fetzer.ch@gmail.com
License: MIT
Download-URL: https://github.com/fetzerch/fritzcollectd/archive/fritzcollectd-0.1.0.tar.gz
Keywords: AVM FritzBox collectd
Platform: UNKNOWN
Classifier: Development Status :: 4 - Beta
Classifier: Environment :: Console
Classifier: Intended Audience :: System Administrators
Classifier: License :: OSI Approved :: MIT License
Classifier: Natural Language :: English
Classifier: Operating System :: POSIX
Classifier: Programming Language :: Python
Classifier: Topic :: System :: Monitoring
Requires-Dist: fritzconnection
